autobf/__init__.py
autobf/example.py
autobf-1.8.2.dist-info/LICENSE
autobf-1.8.2.dist-info/METADATA
autobf-1.8.2.dist-info/WHEEL
autobf-1.8.2.dist-info/top_level.txt
autobf-1.8.2.dist-info/RECORD
