Metadata-Version: 2.1
Name: autobf
Version: 1.8.2
Summary: roblox blox fruit tool
Home-page: https://pypi.org/project/autobf/
Author: KuoYuanLi
Author-email: funny4875@gmail.com
Classifier: Programming Language :: Python :: 3
Classifier: License :: OSI Approved :: MIT License
Classifier: Operating System :: OS Independent
Requires-Python: >=3.6
License-File: LICENSE
Requires-Dist: opencv-contrib-python
Requires-Dist: pyautogui
Requires-Dist: pydirectinput
